nullindustries/__init__.py
nullindustries-0.1.1.dist-info/METADATA
nullindustries-0.1.1.dist-info/WHEEL
nullindustries-0.1.1.dist-info/top_level.txt
nullindustries-0.1.1.dist-info/RECORD
